{
    "56": "56",
    "Aao": "Aao",
    "Agiboya": "Agiboya",
    "Angiboya": "Angiboya",
    "Angigboya": "Angigboya",
    "Angigdoya": "Angigdoya",
    "B. Ngao": "B. Ngao",
    "Ba-Kabotu": "Ba-Kabotu",
    "Ba-Kobotu": "Ba-Kobotu",
    "Baaka": "Baaka",
    "Babawo": "Babawo",
    "Babon": "Babon",
    "Babum": "Babum",
    "Bachalor": "Bachalor",
    "Badarfafeh": "Badarfafeh",
    "Badateteh": "Badateteh",
    "Bafefeh": "Bafefeh",
    "Bafenfeh": "Bafenfeh",
    "Baffienfeh": "Baffienfeh",
    "Bafifeh": "Bafifeh",
    "Bafinfeh": "Bafinfeh",
    "Bafodia": "Bafodia",
    "Bagbo": "Bagbo",
    "Bahoin": "Bahoin",
    "Bahoin/Senjela": "Bahoin/Senjela",
    "Bahoin/Sentaila": "Bahoin/Sentaila",
    "Bai Lagor": "Bai Lagor",
    "Bai Largo": "Bai Largo",
    "Bai P0ll0n": "Bai P0ll0n",
    "Bai Pollon": "Bai Pollon",
    "Bai Polon": "Bai Polon",
    "Bailagor": "Bailagor",
    "Bailargo": "Bailargo",
    "Baimba": "Baimba",
    "Bainyaday": "Bainyaday",
    "Bainyawa": "Bainyawa",
    "Baiwala": "Baiwala",
    "Baiwalla": "Baiwalla",
    "Bakio": "Bakio",
    "Bakoi": "Bakoi",
    "Bakuba": "Bakuba",
    "Balmba": "Balmba",
    "Balwava": "Balwava",
    "Bamba": "Bamba",
    "Bambana": "Bambana",
    "Bambao": "Bambao",
    "Bambara": "Bambara",
    "Bambara Sec": "Bambara Sec",
    "Bambawo": "Bambawo",
    "Bambuibu": "Bambuibu",
    "Bambuibu Tommy": "Bambuibu Tommy",
    "Bambuibuttommy": "Bambuibuttommy",
    "Bambwo": "Bambwo",
    "Bamoi": "Bamoi",
    "Bamwo": "Bamwo",
    "Banbuibu Tommy": "Banbuibu Tommy",
    "Bandafafeh": "Bandafafeh",
    "Banffifeh": "Banffifeh",
    "Banka": "Banka",
    "Banyafeh": "Banyafeh",
    "Banyakor": "Banyakor",
    "Banyanday": "Banyanday",
    "Baoma": "Baoma",
    "Baotihun": "Baotihun",
    "Bapaura": "Bapaura",
    "Bapawa": "Bapawa",
    "Bapewa": "Bapewa",
    "Bapns": "Bapns",
    "Bapus": "Bapus",
    "Barawa": "Barawa",
    "Barawah": "Barawah",
    "Bardu": "Bardu",
    "Barmoi Munu": "Barmoi Munu",
    "Baryegbe": "Baryegbe",
    "Bashaka": "Bashaka",
    "Basiaka": "Basiaka",
    "Basojor": "Basojor",
    "Bassaia": "Bassaia",
    "Bassaia/Songoni": "Bassaia/Songoni",
    "Bassaia/Songonie": "Bassaia/Songonie",
    "Bassiaia": "Bassiaia",
    "Bath Polon": "Bath Polon",
    "Batkanu": "Batkanu",
    "Batpolon": "Batpolon",
    "Bayagba": "Bayagba",
    "Bayagbe": "Bayagbe",
    "Bayegbe": "Bayegbe",
    "Bayenge": "Bayenge",
    "Bayerge": "Bayerge",
    "Baywebe": "Baywebe",
    "Bedehbegu": "Bedehbegu",
    "Bekgrgbor": "Bekgrgbor",
    "Beligaday": "Beligaday",
    "Bembellor": "Bembellor",
    "Bembelor": "Bembelor",
    "Bena": "Bena",
    "Bende Bengu": "Bende Bengu",
    "Bendebaga": "Bendebaga",
    "Bendebega": "Bendebega",
    "Bendebegu": "Bendebegu",
    "Bendebengu": "Bendebengu",
    "Bendega": "Bendega",
    "Bendu": "Bendu",
    "Bendugu": "Bendugu",
    "Bengellor": "Bengellor",
    "Bengelob": "Bengelob",
    "Bengeloh": "Bengeloh",
    "Bengelol": "Bengelol",
    "Benkia": "Benkia",
    "Benna": "Benna",
    "Bevehun": "Bevehun",
    "Beymga": "Beymga",
    "Beyorgboh": "Beyorgboh",
    "Beyorgbor": "Beyorgbor",
    "Bianyawa": "Bianyawa",
    "Bigo": "Bigo",
    "Bilimaia": "Bilimaia",
    "Binkdo2": "Binkdo2",
    "Binkolo": "Binkolo",
    "Binkolo 1": "Binkolo 1",
    "Binkolo 2": "Binkolo 2",
    "Binkolol": "Binkolol",
    "Boama": "Boama",
    "Bobor": "Bobor",
    "Bogboreh": "Bogboreh",
    "Boiwuma": "Boiwuma",
    "Bokoh": "Bokoh",
    "Bokou": "Bokou",
    "Bombeh": "Bombeh",
    "Bombohun": "Bombohun",
    "Bombomwa": "Bombomwa",
    "Bombowa": "Bombowa",
    "Bondoh": "Bondoh",
    "Bondor": "Bondor",
    "Bondor / Mallah": "Bondor / Mallah",
    "Bonffifeh": "Bonffifeh",
    "Bongo": "Bongo",
    "Bongor": "Bongor",
    "Bongre": "Bongre",
    "Bonihun Ngao": "Bonihun Ngao",
    "Bonokor": "Bonokor",
    "Bonthe Island": "Bonthe Island",
    "Bonthe Town": "Bonthe Town",
    "Borawa": "Borawa",
    "Borbo": "Borbo",
    "Borboh": "Borboh",
    "Borbor": "Borbor",
    "Borkou": "Borkou",
    "Borku": "Borku",
    "Borowa": "Borowa",
    "Borowah": "Borowah",
    "Bubiama": "Bubiama",
    "Bubuya": "Bubuya",
    "Bugun": "Bugun",
    "Buima": "Buima",
    "Bullom": "Bullom",
    "Bum": "Bum",
    "Bum Kaku": "Bum Kaku",
    "Bumasadu": "Bumasadu",
    "Bumasodu": "Bumasodu",
    "Bumassadu": "Bumassadu",
    "Bumba": "Bumba",
    "Bumban": "Bumban",
    "Bumeeh": "Bumeeh",
    "Bumkaku": "Bumkaku",
    "Bumpe Benihun": "Bumpe Benihun",
    "Bumpeh": "Bumpeh",
    "Bumpeh Ngao": "Bumpeh Ngao",
    "Bunabu": "Bunabu",
    "Bunabu Section": "Bunabu Section",
    "Bunawa": "Bunawa",
    "Bunkaku": "Bunkaku",
    "Bunubu": "Bunubu",
    "Burkor": "Burkor",
    "Buwuma": "Buwuma",
    "Buyan": "Buyan",
    "Buyram": "Buyram",
    "Bye": "Bye",
    "Bye Section": "Bye Section",
    "Canjohun": "Canjohun",
    "Cental": "Cental",
    "Central": "Central",
    "Central Kargoi": "Central Kargoi",
    "Chepo": "Chepo",
    "Coromboya": "Coromboya",
    "Cortugbu": "Cortugbu",
    "Cubina": "Cubina",
    "D0d0": "D0d0",
    "Dababa": "Dababa",
    "Dabeni": "Dabeni",
    "Dabolah": "Dabolah",
    "Dagalaga": "Dagalaga",
    "Dakaleley": "Dakaleley",
    "Dakoakal": "Dakoakal",
    "Dakona": "Dakona",
    "Dakona Perri": "Dakona Perri",
    "Dakonah": "Dakonah",
    "Dalenga": "Dalenga",
    "Damai": "Damai",
    "Dan Sei": "Dan Sei",
    "Dangbaidu": "Dangbaidu",
    "Dasei": "Dasei",
    "Dayie": "Dayie",
    "Dea/Sienga": "Dea/Sienga",
    "Deilenga": "Deilenga",
    "Delenga": "Delenga",
    "Dellenga": "Dellenga",
    "Dema": "Dema",
    "Dembelor": "Dembelor",
    "Denjehun": "Denjehun",
    "Dewallu": "Dewallu",
    "Dewalu": "Dewalu",
    "Dia": "Dia",
    "Dodo": "Dodo",
    "Dogoloya": "Dogoloya",
    "Dojoloya": "Dojoloya",
    "Dokona": "Dokona",
    "Dukpumbu": "Dukpumbu",
    "Duramania": "Duramania",
    "F0r0nk0ya": "F0r0nk0ya",
    "Fadu": "Fadu",
    "Fadugu Madigo": "Fadugu Madigo",
    "Fadugu Madingo": "Fadugu Madingo",
    "Fadugu Ndingowa": "Fadugu Ndingowa",
    "Fahbaina": "Fahbaina",
    "Fairowlo": "Fairowlo",
    "Fakoi": "Fakoi",
    "Falaba": "Falaba",
    "Falaba 1": "Falaba 1",
    "Falaba 11": "Falaba 11",
    "Falaba 2": "Falaba 2",
    "Falaba- 1": "Falaba- 1",
    "Falaba- 2": "Falaba- 2",
    "Falaba1": "Falaba1",
    "Falaba11": "Falaba11",
    "Falaba2": "Falaba2",
    "Falaba3": "Falaba3",
    "Falaba4": "Falaba4",
    "Falaba5": "Falaba5",
    "Falawiya": "Falawiya",
    "Falay": "Falay",
    "Faleunya": "Faleunya",
    "Falewuja": "Falewuja",
    "Faley": "Faley",
    "Fallay": "Fallay",
    "Fallewuja": "Fallewuja",
    "Falley": "Falley",
    "Falloh": "Falloh",
    "Fally": "Fally",
    "Fally / Nyawa": "Fally / Nyawa",
    "Falon": "Falon",
    "Falor": "Falor",
    "Falubu2": "Falubu2",
    "Famgbangoes": "Famgbangoes",
    "Fanima": "Fanima",
    "Fanima [2]": "Fanima [2]",
    "Farlor": "Farlor",
    "Fauya": "Fauya",
    "Fiama": "Fiama",
    "Fikie": "Fikie",
    "Filkie": "Filkie",
    "Fogbo": "Fogbo",
    "Foindu": "Foindu",
    "Foiya": "Foiya",
    "Fondu": "Fondu",
    "Forbgo": "Forbgo",
    "Fore Road Baka": "Fore Road Baka",
    "Foredugu": "Foredugu",
    "Forgbo": "Forgbo",
    "Forma": "Forma",
    "Foronkoya": "Foronkoya",
    "Fortumboyie": "Fortumboyie",
    "Foryah": "Foryah",
    "Fothombugie": "Fothombugie",
    "Foya": "Foya",
    "Foyah": "Foyah",
    "Fudu": "Fudu",
    "Fulawahun": "Fulawahun",
    "Futa": "Futa",
    "Futa P West": "Futa P West",
    "Futa Pejeh East": "Futa Pejeh East",
    "G.penni": "G.penni",
    "G/Tetema": "G/Tetema",
    "Gabom": "Gabom",
    "Gabongeh": "Gabongeh",
    "Gaindema": "Gaindema",
    "Galeness Perri": "Galeness Perri",
    "Gambia": "Gambia",
    "Gandina": "Gandina",
    "Gandorhun": "Gandorhun",
    "Gandorn": "Gandorn",
    "Ganya": "Ganya",
    "Gao": "Gao",
    "Gardorhun": "Gardorhun",
    "Gargbe": "Gargbe",
    "Gawuima": "Gawuima",
    "Gbaama": "Gbaama",
    "Gbabai": "Gbabai",
    "Gbaima": "Gbaima",
    "Gbaingbatoke": "Gbaingbatoke",
    "Gbainkafay": "Gbainkafay",
    "Gbainkfay": "Gbainkfay",
    "Gbainkfey": "Gbainkfey",
    "Gbakahun": "Gbakahun",
    "Gballan": "Gballan",
    "Gbama": "Gbama",
    "Gbambassa": "Gbambassa",
    "Gbame Kandor": "Gbame Kandor",
    "Gbana/Znaani": "Gbana/Znaani",
    "Gbanakandor": "Gbanakandor",
    "Gbane": "Gbane",
    "Gbane Kandor": "Gbane Kandor",
    "Gbane Tetema": "Gbane Tetema",
    "Gbane Tetemah": "Gbane Tetemah",
    "Gbanekandor": "Gbanekandor",
    "Gbangbatok": "Gbangbatok",
    "Gbangbatoke": "Gbangbatoke",
    "Gbangbatoko": "Gbangbatoko",
    "Gbankfay": "Gbankfay",
    "Gbap": "Gbap",
    "Gbara Kamba": "Gbara Kamba",
    "Gbaran Kamba": "Gbaran Kamba",
    "Gbayafe": "Gbayafe",
    "Gbeahan": "Gbeahan",
    "Gbehan": "Gbehan",
    "Gbehia": "Gbehia",
    "Gbela": "Gbela",
    "Gbema Tetema": "Gbema Tetema",
    "Gbemata": "Gbemata",
    "Gbembo": "Gbembo",
    "Gbendebu": "Gbendebu",
    "Gbendembu": "Gbendembu",
    "Gbendemdu": "Gbendemdu",
    "Gbendenbu": "Gbendenbu",
    "Gbendu": "Gbendu",
    "Gbengain": "Gbengain",
    "Gbenkfay": "Gbenkfay",
    "Gbense": "Gbense",
    "Gbera-Kamba": "Gbera-Kamba",
    "Gberay-Bana": "Gberay-Bana",
    "Gberay-Thunkara": "Gberay-Thunkara",
    "Gbereybana": "Gbereybana",
    "Gberia Fotubu": "Gberia Fotubu",
    "Gberia Timbakor": "Gberia Timbakor",
    "Gberray Bana": "Gberray Bana",
    "Gberray Morie": "Gberray Morie",
    "Gberray Thunkara": "Gberray Thunkara",
    "Gbindi": "Gbindi",
    "Gbindi Central": "Gbindi Central",
    "Gbinle": "Gbinle",
    "Gbinleh": "Gbinleh",
    "Gbo": "Gbo",
    "Gbo Sec.": "Gbo Sec.",
    "Gbobana": "Gbobana",
    "Gbogary": "Gbogary",
    "Gbogboafeh": "Gbogboafeh",
    "Gbogborafe": "Gbogborafe",
    "Gbogray": "Gbogray",
    "Gboika": "Gboika",
    "Gbokobor": "Gbokobor",
    "Gbomokor": "Gbomokor",
    "Gbomoti": "Gbomoti",
    "Gbomotie": "Gbomoti",
    "Gbonda": "Gbonda",
    "Gbondu": "Gbondu",
    "Gbondu Bum": "Gbondu Bum",
    "Gbondubum": "Gbondubum",
    "Gbonduhum": "Gbonduhum",
    "Gbonge": "Gbonge",
    "Gbongeh": "Gbongeh",
    "Gbongre": "Gbongre",
    "Gbonka": "Gbonka",
    "Gbonko Mayira": "Gbonko Mayira",
    "Gbonkobor": "Gbonkobor",
    "Gbonkomayira": "Gbonkomayira",
    "Gborbana": "Gborbana",
    "Gelehun": "Gelehun",
    "Gendema": "Gendema",
    "Gendema 1": "Gendema 1",
    "Gendema 2": "Gendema 2",
    "Gendema Ii": "Gendema Ii",
    "Gendewa": "Gendewa",
    "Gendima": "Gendima",
    "Gere-Morie": "Gere-Morie",
    "Gibima": "Gibima",
    "Gibina": "Gibina",
    "Gibma": "Gibma",
    "Gibo": "Gibo",
    "Giehun": "Giehun",
    "Gindohun": "Gindohun",
    "Gobaru 1": "Gobaru 1",
    "Gobaru 2": "Gobaru 2",
    "Gobaru I": "Gobaru I",
    "Gobaru Ii": "Gobaru Ii",
    "Gola": "Gola",
    "Golama": "Golama",
    "Goleiwoma": "Goleiwoma",
    "Golewoma": "Golewoma",
    "Golu": "Golu",
    "Gondama": "Gondama",
    "Gorapon": "Gorapon",
    "Greema": "Greema",
    "Greema Loko": "Greema Loko",
    "Grema": "Grema",
    "Hahun": "Hahun",
    "Hajlah": "Hajlah",
    "Hanjie": "Hanjie",
    "Helegbema": "Helegbema",
    "Heremakono": "Heremakono",
    "I": "I",
    "Island": "Island",
    "J .Massa": "J .Massa",
    "J-Massaaw": "J-Massaaw",
    "Jaa": "Jaa",
    "Jabama": "Jabama",
    "Jafasa": "Jafasa",
    "Jaiafeh": "Jaiafeh",
    "Jaiama": "Jaiama",
    "Jaikor": "Jaikor",
    "Jaima": "Jaima",
    "Jakema": "Jakema",
    "Janema": "Janema",
    "Jango": "Jango",
    "Jassande Keifema": "Jassande Keifema",
    "Jassed Ngobma": "Jassed Ngobma",
    "Jassende Kpeima": "Jassende Kpeima",
    "Jassende Ngoleima": "Jassende Ngoleima",
    "Jassendeh": "Jassendeh",
    "Jassendeh Ngolama": "Jassendeh Ngolama",
    "Jassendoh Ngolama": "Jassendoh Ngolama",
    "Jayahum": "Jayahum",
    "Jayahun": "Jayahun",
    "Jeigbleh": "Jeigbleh",
    "Jejehun": "Jejehun",
    "Jessendeh Ngolama": "Jessendeh Ngolama",
    "Jewoh": "Jewoh",
    "Jimmi": "Jimmi",
    "Jimmy": "Jimmy",
    "Jimmylah": "Jimmylah",
    "Jimulah": "Jimulah",
    "Jonga": "Jonga",
    "Jongar": "Jongar",
    "Jongba": "Jongba",
    "Jongo": "Jongo",
    "Jongoni": "Jongoni",
    "Jongor": "Jongor",
    "Jorwu": "Jorwu",
    "Jougba": "Jougba",
    "Jougba/Kajei": "Jougba/Kajei",
    "Jougbu": "Jougbu",
    "Joya": "Joya",
    "Joyabu": "Joyabu",
    "Joyah": "Joyah",
    "Jrowu": "Jrowu",
    "Kaamai": "Kaamai",
    "Kaargbavu": "Kaargbavu",
    "Kaball": "Kaball",
    "Kabata": "Kabata",
    "Kabatha": "Kabatha",
    "Kabaya": "Kabaya",
    "Kabgaran": "Kabgaran",
    "Kabondeh": "Kabondeh",
    "Kabonka": "Kabonka",
    "Kadanso": "Kadanso",
    "Kaduawo": "Kaduawo",
    "Kaduowo": "Kaduowo",
    "Kaduowo / Tawova": "Kaduowo / Tawova",
    "Kafala": "Kafala",
    "Kafala 1": "Kafala 1",
    "Kafala 1]": "Kafala 1]",
    "Kafala 2": "Kafala 2",
    "Kafala 2]": "Kafala 2]",
    "Kafala 3": "Kafala 3",
    "Kafala 4": "Kafala 4",
    "Kafala 5": "Kafala 5",
    "Kafala Ii": "Kafala Ii",
    "Kafalla": "Kafalla",
    "Kafalla 2": "Kafalla 2",
    "Kagaka": "Kagaka",
    "Kagbala": "Kagbala",
    "Kagbara": "Kagbara",
    "Kagbara 1": "Kagbara 1",
    "Kagbara 1]": "Kagbara 1]",
    "Kagbara 2": "Kagbara 2",
    "Kagbara A": "Kagbara A",
    "Kagbara Ii": "Kagbara Ii",
    "Kagbara Ll": "Kagbara Ll",
    "Kagbaran": "Kagbaran",
    "Kagbaran 1": "Kagbaran 1",
    "Kagbaran 2": "Kagbaran 2",
    "Kagbaran 2]": "Kagbaran 2]",
    "Kagbaran Dokom": "Kagbaran Dokom",
    "Kagbaran Dokom 1": "Kagbaran Dokom 1",
    "Kagbaran Dokom 2": "Kagbaran Dokom 2",
    "Kagbaran Dokum": "Kagbaran Dokum",
    "Kagbaran Dokum 2": "Kagbaran Dokum 2",
    "Kagbaran Donkom 1": "Kagbaran Donkom 1",
    "Kagbaran I": "Kagbaran I",
    "Kagbaran Ii": "Kagbaran Ii",
    "Kagbaraw": "Kagbaraw",
    "Kagbo": "Kagbo",
    "Kagbo 1": "Kagbo 1",
    "Kagbo 11": "Kagbo 11",
    "Kagbo1": "Kagbo1",
    "Kagbo11": "Kagbo11",
    "Kagbo2": "Kagbo2",
    "Kagboi": "Kagboi",
    "Kagbtiba": "Kagbtiba",
    "Kahaimo": "Kahaimo",
    "Kahekay": "Kahekay",
    "Kahemoh": "Kahemoh",
    "Kaimkakolo": "Kaimkakolo",
    "Kaimpkkolo": "Kaimpkkolo",
    "Kaindama": "Kaindama",
    "Kaindema": "Kaindema",
    "Kaio": "Kaio",
    "Kaizobo": "Kaizobo",
    "Kaizoboi": "Kaizoboi",
    "Kajei": "Kajei",
    "Kakpanda": "Kakpanda",
    "Kalangba": "Kalangba",
    "Kalansa": "Kalansa",
    "Kalasokoda": "Kalasokoda",
    "Kalaugba": "Kalaugba",
    "Kalia": "Kalia",
    "Kalian": "Kalian",
    "Kallian": "Kallian",
    "Kalooka": "Kalooka",
    "Kama": "Kama",
    "Kama Teng": "Kama Teng",
    "Kama Toh": "Kama Toh",
    "Kamabeh Kaue": "Kamabeh Kaue",
    "Kamai": "Kamai",
    "Kamakuie": "Kamakuie",
    "Kamakuwe": "Kamakuwe",
    "Kamakuwei": "Kamakuwei",
    "Kamakwie": "Kamakwie",
    "Kamalo": "Kamalo",
    "Kamalu": "Kamalu",
    "Kamara": "Kamara",
    "Kamaranka": "Kamaranka",
    "Kamasondo": "Kamasondo",
    "Kamassasa": "Kamassasa",
    "Kamassassa": "Kamassassa",
    "Kamasunu": "Kamasunu",
    "Kamba": "Kamba",
    "Kambia": "Kambia",
    "Kambotoke": "Kambotoke",
    "Kamia": "Kamia",
    "Kamiendor": "Kamiendor",
    "Kanbouleh": "Kanbouleh",
    "Kanda Town": "Kanda Town",
    "Kandor": "Kandor",
    "Kandorlah": "Kandorlah",
    "Kanela": "Kanela",
    "Kanga": "Kanga",
    "Kangama": "Kangama",
    "Kangebai": "Kangebai",
    "Kania": "Kania",
    "Kanikorie": "Kanikorie",
    "Kankama": "Kankama",
    "Kankan": "Kankan",
    "Kanu": "Kanu",
    "Kanya": "Kanya",
    "Kaoro": "Kaoro",
    "Kapuima": "Kapuima",
    "Karala[1]": "Karala[1]",
    "Kargbavu": "Kargbavu",
    "Kargbevu": "Kargbevu",
    "Kargbo": "Kargbo",
    "Kargbo 1": "Kargbo 1",
    "Kargbo 2": "Kargbo 2",
    "Kargbo I": "Kargbo I",
    "Kargbo Ii": "Kargbo Ii",
    "Kargbou": "Kargbou",
    "Kargbulor": "Kargbulor",
    "Kargbvu": "Kargbvu",
    "Karjei": "Karjei",
    "Karlu": "Karlu",
    "Karngebai": "Karngebai",
    "Karngebei": "Karngebei",
    "Kasala L": "Kasala L",
    "Kasemgbeh": "Kasemgbeh",
    "Kasengbeh": "Kasengbeh",
    "Kasipoto": "Kasipoto",
    "Kasocra": "Kasocra",
    "Kasokira": "Kasokira",
    "Kasongha": "Kasongha",
    "Kassipoto": "Kassipoto",
    "Kasuko": "Kasuko",
    "Kasunko": "Kasunko",
    "Katalan": "Katalan",
    "Kataway": "Kataway",
    "Kathakary": "Kathakary",
    "Kathakay": "Kathakay",
    "Kathakaya": "Kathakaya",
    "Kathakayan": "Kathakayan",
    "Kathakayon": "Kathakayon",
    "Kathakayowboli": "Kathakayowboli",
    "Kathamtha": "Kathamtha",
    "Kathanka": "Kathanka",
    "Kathantha": "Kathantha",
    "Kathanthan": "Kathanthan",
    "Kathanthineh": "Kathanthineh",
    "Kathegeya": "Kathegeya",
    "Kathekagon": "Kathekagon",
    "Kathekaya": "Kathekaya",
    "Kathekkeyar": "Kathekkeyar",
    "Kawula": "Kawula",
    "Kayaka": "Kayaka",
    "Kayakasa": "Kayakasa",
    "Kayassi": "Kayassi",
    "Kayassie": "Kayassie",
    "Kayassie(Mabamba)": "Kayassie(Mabamba)",
    "Kayenkassa": "Kayenkassa",
    "Kayimbor": "Kayimbor",
    "Keange": "Keange",
    "Kebail": "Kebail",
    "Kebawana": "Kebawana",
    "Kefima": "Kefima",
    "Keimaya": "Keimaya",
    "Keisua": "Keisua",
    "Kelian": "Kelian",
    "Kemaya": "Kemaya",
    "Kemeding": "Kemeding",
    "Kemedugu": "Kemedugu",
    "Kemedunu": "Kemedunu",
    "Kemeya": "Kemeya",
    "Kemoh": "Kemoh",
    "Kemokai": "Kemokai",
    "Kemokai Zoker 1": "Kemokai Zoker 1",
    "Kemokai Zoker1": "Kemokai Zoker1",
    "Kemokai Zoker2": "Kemokai Zoker2",
    "Kemokai Zoker3": "Kemokai Zoker3",
    "Kemokai Zoker4": "Kemokai Zoker4",
    "Kemudu": "Kemudu",
    "Kendabo": "Kendabo",
    "Kendebo": "Kendebo",
    "Kendebu": "Kendebu",
    "Kenema": "Kenema",
    "Kenewa": "Kenewa",
    "Kengo": "Kengo",
    "Kengo-Soro": "Kengo-Soro",
    "Kenzo": "Kenzo",
    "Kesua": "Kesua",
    "Ketaway": "Ketaway",
    "Ketims": "Ketims",
    "Keuella": "Keuella",
    "Kewoh": "Kewoh",
    "Keymaya": "Keymaya",
    "Khahekay": "Khahekay",
    "Khahekay/Babum": "Khahekay/Babum",
    "Kia Zombo": "Kia Zombo",
    "Kiamp Kakolo": "Kiamp Kakolo",
    "Kiazoboi": "Kiazoboi",
    "Kiazogboi": "Kiazogboi",
    "Kiemaya": "Kiemaya",
    "Kimaya": "Kimaya",
    "Kindia": "Kindia",
    "Kindiya": "Kindiya",
    "Koaro": "Koaro",
    "Kodogbe": "Kodogbe",
    "Kofurgba": "Kofurgba",
    "Koi0dugu": "Koi0dugu",
    "Koidu": "Koidu",
    "Koilenga": "Koilenga",
    "Koilenga/Pejeh West": "Koilenga/Pejeh West",
    "Koimato": "Koimato",
    "Koinadugu": "Koinadugu",
    "Koindema": "Koindema",
    "Koindu Kuna": "Koindu Kuna",
    "Koino": "Koino",
    "Kojeh": "Kojeh",
    "Kokongokuma": "Kokongokuma",
    "Kom 2": "Kom 2",
    "Komadu": "Komadu",
    "Komende": "Komende",
    "Komrabai Waterloo": "Komrabai Waterloo",
    "Kondaeto": "Kondaeto",
    "Kondembaia": "Kondembaia",
    "Kondogbeh": "Kondogbeh",
    "Kondorlah": "Kondorlah",
    "Kongbelfeh": "Kongbelfeh",
    "Konglefeh": "Konglefeh",
    "Kongofinja": "Kongofinja",
    "Kongofinjoh": "Kongofinjoh",
    "Kongonfenjah": "Kongonfenjah",
    "Kongonyendal": "Kongonyendal",
    "Kongotejar": "Kongotejar",
    "Konia": "Konia",
    "Konio": "Konio",
    "Konkorie": "Konkorie",
    "Konta": "Konta",
    "Konta Kargbo": "Konta Kargbo",
    "Koo Kongokuma": "Koo Kongokuma",
    "Koodu": "Koodu",
    "Kookomgokuma": "Kookomgokuma",
    "Kookongokuma": "Kookongokuma",
    "Kookongorkuma": "Kookongorkuma",
    "Kooma": "Kooma",
    "Koomo": "Koomo",
    "Koonkongsoma": "Koonkongsoma",
    "Kopala Ll": "Kopala Ll",
    "Koray": "Koray",
    "Korjeh": "Korjeh",
    "Koroboya": "Koroboya",
    "Koromboya": "Koromboya",
    "Kortiya": "Kortiya",
    "Kortugbu": "Kortugbu",
    "Korwa": "Korwa",
    "Korwah": "Korwah",
    "Kotgbu": "Kotgbu",
    "Koturgbu/Mewah": "Koturgbu/Mewah",
    "Kovella": "Kovella",
    "Kowa": "Kowa",
    "Koyan": "Koyan",
    "Kpaewa": "Kpaewa",
    "Kpagbalia": "Kpagbalia",
    "Kpagia": "Kpagia",
    "Kpaiwa": "Kpaiwa",
    "Kpallay": "Kpallay",
    "Kpandobu": "Kpandobu",
    "Kpandubu": "Kpandubu",
    "Kpanga": "Kpanga",
    "Kpanga 1": "Kpanga 1",
    "Kpanga 2": "Kpanga 2",
    "Kpanga Ii": "Kpanga Ii",
    "Kpanga Kabbordeh": "Kpanga Kabbordeh",
    "Kpanga Koimato": "Kpanga Koimato",
    "Kpangbalia": "Kpangbalia",
    "Kpangballa": "Kpangballa",
    "Kpangballia": "Kpangballia",
    "Kpange": "Kpange",
    "Kpangia": "Kpangia",
    "Kpanglagho": "Kpanglagho",
    "Kpanglago": "Kpanglago",
    "Kpanguglo": "Kpanguglo",
    "Kpangulgo": "Kpangulgo",
    "Kpangulugo": "Kpangulugo",
    "Kpanguma": "Kpanguma",
    "Kpanje": "Kpanje",
    "Kpanka Koimato": "Kpanka Koimato",
    "Kpavilem": "Kpavilem",
    "Kpefema": "Kpefema",
    "Kpemaya": "Kpemaya",
    "Kpemdema": "Kpemdema",
    "Kpendema": "Kpendema",
    "Kpetema": "Kpetema",
    "Kpindima": "Kpindima",
    "Kposohr": "Kposohr",
    "Kpungigho": "Kpungigho",
    "Kukuna": "Kukuna",
    "Kulakor": "Kulakor",
    "Kumabeh-Kwe": "Kumabeh-Kwe",
    "Kumabeh/Kore": "Kumabeh/Kore",
    "Kumabeh/Kwe": "Kumabeh/Kwe",
    "Kumabela/Kwe": "Kumabela/Kwe",
    "Kumaya": "Kumaya",
    "Kumrabai": "Kumrabai",
    "Kundonwa": "Kundonwa",
    "Kunyafoi": "Kunyafoi",
    "Kunyajoi": "Kunyajoi",
    "Kunyatoi": "Kunyatoi",
    "Kurngebai": "Kurngebai",
    "Kussipoto": "Kussipoto",
    "Kutay": "Kutay",
    "Kutey": "Kutey",
    "Kuttay": "Kuttay",
    "Kwidu": "Kwidu",
    "L.kayaimba": "L.kayaimba",
    "L.pemba": "L.pemba",
    "L/Kayamba": "L/Kayamba",
    "Lahun": "Lahun",
    "Laimba": "Laimba",
    "Lal Lenken": "Lal Lenken",
    "Lal-Lenken": "Lal-Lenken",
    "Lalenken": "Lalenken",
    "Laminay": "Laminay",
    "Laminaya": "Laminaya",
    "Laminaya Loko": "Laminaya Loko",
    "Laminaya Soso": "Laminaya Soso",
    "Laminayasoso": "Laminayasoso",
    "Land Ngene": "Land Ngene",
    "Landi Nere": "Landi Nere",
    "Landi Ngere": "Landi Ngere",
    "Langei": "Langei",
    "Langie": "Langie",
    "Lango": "Lango",
    "Lanje": "Lanje",
    "Lanjei": "Lanjei",
    "Lanji": "Lanji",
    "Lanjie": "Lanjie",
    "Largo": "Largo",
    "Largoh": "Largoh",
    "Lawana": "Lawana",
    "Lei": "Lei",
    "Lei Section": "Lei Section",
    "Lela": "Lela",
    "Levuma": "Levuma",
    "Levuma Jeibla": "Levuma Jeibla",
    "Lie": "Lie",
    "Lilahuwahun": "Lilahuwahun",
    "Limba": "Limba",
    "Limbaia": "Limbaia",
    "Limbaya": "Limbaya",
    "Limbo Kabo": "Limbo Kabo",
    "Lohindie": "Lohindie",
    "Loko-Madina": "Loko-Madina",
    "Loweekaya": "Loweekaya",
    "Lower": "Lower",
    "Lower Baimba": "Lower Baimba",
    "Lower Baimber": "Lower Baimber",
    "Lower Boimba": "Lower Boimba",
    "Lower Geoma": "Lower Geoma",
    "Lower Giebu": "Lower Giebu",
    "Lower Kaigo": "Lower Kaigo",
    "Lower Kaigoi": "Lower Kaigoi",
    "Lower Kaigor": "Lower Kaigor",
    "Lower Kaiyamba": "Lower Kaiyamba",
    "Lower Kama": "Lower Kama",
    "Lower Kargo": "Lower Kargo",
    "Lower Kargoi": "Lower Kargoi",
    "Lower Kayairba": "Lower Kayairba",
    "Lower Kayamba": "Lower Kayamba",
    "Lower Kayemba": "Lower Kayemba",
    "Lower Kayimba": "Lower Kayimba",
    "Lower Kema": "Lower Kema",
    "Lower Kpombai": "Lower Kpombai",
    "Lower Kpombali": "Lower Kpombali",
    "Lower Kuiva": "Lower Kuiva",
    "Lower Kuvia": "Lower Kuvia",
    "Lower Lei": "Lower Lei",
    "Lower Ngiebu": "Lower Ngiebu",
    "Lower Niawa": "Lower Niawa",
    "Lower Nyama": "Lower Nyama",
    "Lower Nyawa": "Lower Nyawa",
    "Lower Nyawa/Lower Baimba": "Lower Nyawa/Lower Baimba",
    "Lower Pamba": "Lower Pamba",
    "Lower Pataloo": "Lower Pataloo",
    "Lower Patloo": "Lower Patloo",
    "Lower Pemba": "Lower Pemba",
    "Lower Quiva": "Lower Quiva",
    "Lower Sami": "Lower Sami",
    "Lower Samie": "Lower Samie",
    "Lower Section": "Lower Section",
    "Lower-Niawa": "Lower-Niawa",
    "Lower/Samie": "Lower/Samie",
    "Luawa": "Luawa",
    "Luawa Foguiya": "Luawa Foguiya",
    "Luawa Foiya": "Luawa Foiya",
    "Luawa Foya": "Luawa Foya",
    "Luawa Yiehun": "Luawa Yiehun",
    "Luawayiehun": "Luawayiehun",
    "Luinya": "Luinya",
    "Luma": "Luma",
    "Lunga": "Lunga",
    "Lungi": "Lungi",
    "Lungie": "Lungie",
    "Lungiii": "Lungiii",
    "Lungile": "Lungile",
    "Lungili": "Lungili",
    "Lunia": "Lunia",
    "Lunya": "Lunya",
    "Luwana": "Luwana",
    "Ma Koray": "Ma Koray",
    "Maajeh": "Maajeh",
    "Maawonkara": "Maawonkara",
    "Maayeppoh": "Maayeppoh",
    "Mab.mende": "Mab.mende",
    "Mabai": "Mabai",
    "Mabamba": "Mabamba",
    "Mabanba": "Mabanba",
    "Mabang": "Mabang",
    "Mabang/Marunia": "Mabang/Marunia",
    "Mabanta": "Mabanta",
    "Mabelifu": "Mabelifu",
    "Mabgbeni": "Mabgbeni",
    "Mabilafu": "Mabilafu",
    "Maboboh": "Maboboh",
    "Maboboh Koray": "Maboboh Koray",
    "Mabobohkor": "Mabobohkor",
    "Maboni": "Maboni",
    "Mabonie": "Mabonie",
    "Mabonto": "Mabonto",
    "Mabontor": "Mabontor",
    "Maborbor": "Maborbor",
    "Maborbor-Koray": "Maborbor-Koray",
    "Mabureh Buya": "Mabureh Buya",
    "Mabureh Mende": "Mabureh Mende",
    "Macteboi": "Macteboi",
    "Madigbo": "Madigbo",
    "Madina": "Madina",
    "Madina Gbonkobon": "Madina Gbonkobon",
    "Madina Gbonkobor": "Madina Gbonkobor",
    "Madina Loko": "Madina Loko",
    "Madoma": "Madoma",
    "Mafaray": "Mafaray",
    "Mafindor": "Mafindor",
    "Mafinkor": "Mafinkor",
    "Mafonda": "Mafonda",
    "Mafonikay": "Mafonikay",
    "Maforay": "Maforay",
    "Magay Loko": "Magay Loko",
    "Magbafth": "Magbafth",
    "Magbaimba": "Magbaimba",
    "Magbaingba": "Magbaingba",
    "Magbala Makabo": "Magbala Makabo",
    "Magbankitha": "Magbankitha",
    "Magbao": "Magbao",
    "Magbapsa": "Magbapsa",
    "Magbaringba": "Magbaringba",
    "Magbela Makabo": "Magbela Makabo",
    "Magbele": "Magbele",
    "Magbengbeh": "Magbengbeh",
    "Magbeni": "Magbeni",
    "Magbenie": "Magbenie",
    "Magbenteh": "Magbenteh",
    "Magboingba": "Magboingba",
    "Magbonkani 11": "Magbonkani 11",
    "Magbonkanie Ii": "Magbonkanie Ii",
    "Magbonkeni": "Magbonkeni",
    "Magbonkoni 2": "Magbonkoni 2",
    "Magbonkonie": "Magbonkonie",
    "Magbonkonie 2": "Magbonkonie 2",
    "Mahera": "Mahera",
    "Mai": "Mai",
    "Mainandor": "Mainandor",
    "Maindekoh": "Maindekoh",
    "Maindekomedeh": "Maindekomedeh",
    "Maindekor": "Maindekor",
    "Maindekornedeh": "Maindekornedeh",
    "Mainkandor": "Mainkandor",
    "Mainkondor": "Mainkondor",
    "Makaba": "Makaba",
    "Makaframday": "Makaframday",
    "Makagambay": "Makagambay",
    "Makai": "Makai",
    "Makairaimbay": "Makairaimbay",
    "Makali": "Makali",
    "Makalie": "Makalie",
    "Makama": "Makama",
    "Makamba": "Makamba",
    "Makamp": "Makamp",
    "Makamray": "Makamray",
    "Makar": "Makar",
    "Makathe(Massapi)": "Makathe(Massapi)",
    "Makayambu": "Makayambu",
    "Makaynambay": "Makaynambay",
    "Makayrambay": "Makayrambay",
    "Makayrembay": "Makayrembay",
    "Makayyambay": "Makayyambay",
    "Makeifa": "Makeifa",
    "Makelfa": "Makelfa",
    "Makeni": "Makeni",
    "Makerewo": "Makerewo",
    "Makery": "Makery",
    "Maketeh": "Maketeh",
    "Makey": "Makey",
    "Makiteh": "Makiteh",
    "Makneh Bama": "Makneh Bama",
    "Makoba": "Makoba",
    "Makolun": "Makolun",
    "Makombom": "Makombom",
    "Makomray": "Makomray",
    "Makong": "Makong",
    "Makonkorie": "Makonkorie",
    "Makontandae": "Makontandae",
    "Makontanday": "Makontanday",
    "Makontande": "Makontande",
    "Makontandy": "Makontandy",
    "Makonthandae": "Makonthandae",
    "Makony": "Makony",
    "Makorbolai": "Makorbolai",
    "Makorobolai": "Makorobolai",
    "Makragbeh": "Makragbeh",
    "Makrubeh": "Makrubeh",
    "Makrugbah": "Makrugbah",
    "Makrugbeh": "Makrugbeh",
    "Makulon": "Makulon",
    "Makump": "Makump",
    "Malakuray": "Malakuray",
    "Malal": "Malal",
    "Malalon": "Malalon",
    "Malaykuray": "Malaykuray",
    "Maleboi": "Maleboi",
    "Mallah": "Mallah",
    "Mallah Peni": "Mallah Peni",
    "Malua Rolankonoh": "Malua Rolankonoh",
    "Malua Rolonkonoh": "Malua Rolonkonoh",
    "Mamaka": "Mamaka",
    "Mamamso Sanka": "Mamamso Sanka",
    "Mamangewo": "Mamangewo",
    "Mamanjawo": "Mamanjawo",
    "Mamank0h": "Mamank0h",
    "Mamanke": "Mamanke",
    "Mamanki": "Mamanki",
    "Mamankie": "Mamankie",
    "Mamankoh": "Mamankoh",
    "Mamankol": "Mamankol",
    "Mamanso": "Mamanso",
    "Mamanso Sanka": "Mamanso Sanka",
    "Mamasonko Sanka": "Mamasonko Sanka",
    "Mamatha": "Mamatha",
    "Mambawa": "Mambawa",
    "Mambie": "Mambie",
    "Mambolo": "Mambolo",
    "Mamboma": "Mamboma",
    "Mamo River": "Mamo River",
    "Mamonkoh": "Mamonkoh",
    "Mamonso Sanka": "Mamonso Sanka",
    "Mamunta": "Mamunta",
    "Mamuntha": "Mamuntha",
    "Mamurie": "Mamurie",
    "Mamuwa": "Mamuwa",
    "Man0": "Man0",
    "Man0-1": "Man0-1",
    "Man0-2": "Man0-2",
    "Manan": "Manan",
    "Manary": "Manary",
    "Manathi": "Manathi",
    "Manathie": "Manathie",
    "Mandeteh": "Mandeteh",
    "Mando": "Mando",
    "Mandrefeh": "Mandrefeh",
    "Mandrerefet": "Mandrerefet",
    "Mandu": "Mandu",
    "Maneh": "Maneh",
    "Manewa": "Manewa",
    "Mangalu": "Mangalu",
    "Mangay": "Mangay",
    "Mangay Baba": "Mangay Baba",
    "Mangay Bama": "Mangay Bama",
    "Mangay Bana": "Mangay Bana",
    "Mangay Bara": "Mangay Bara",
    "Mangay Buna": "Mangay Buna",
    "Mangay Loko": "Mangay Loko",
    "Mangaybana": "Mangaybana",
    "Mangaybureh": "Mangaybureh",
    "Mange": "Mange",
    "Mange-bana": "Mange-bana",
    "Mangrefeh": "Mangrefeh",
    "Mangula": "Mangula",
    "Maninga": "Maninga",
    "Manjama": "Manjama",
    "Manjehun": "Manjehun",
    "Manjeihu": "Manjeihu",
    "Manjeihum": "Manjeihum",
    "Manjeihun": "Manjeihun",
    "Mankaneh": "Mankaneh",
    "Mankaneh Bana 2": "Mankaneh Bana 2",
    "Mankene": "Mankene",
    "Mankene Bana 1": "Mankene Bana 1",
    "Mankene Bana 2": "Mankene Bana 2",
    "Mankeneh": "Mankeneh",
    "Mankeneh Bana 1": "Mankeneh Bana 1",
    "Mankeneh Bana 2": "Mankeneh Bana 2",
    "Mankenh": "Mankenh",
    "Manknch Bana": "Manknch Bana",
    "Manknebana 2": "Manknebana 2",
    "Mankneh Bama": "Mankneh Bama",
    "Mankneh Bana 1": "Mankneh Bana 1",
    "Mankneh Bana 2": "Mankneh Bana 2",
    "Mankrie Bana Ii": "Mankrie Bana Ii",
    "Manlseneh": "Manlseneh",
    "Manna": "Manna",
    "Manna 1": "Manna 1",
    "Manna 2": "Manna 2",
    "Manna-1": "Manna-1",
    "Manna-2": "Manna-2",
    "Mannah": "Mannah",
    "Manni": "Manni",
    "Manniga": "Manniga",
    "Manninga": "Manninga",
    "Mano": "Mano",
    "Mano 1": "Mano 1",
    "Mano 2": "Mano 2",
    "Mano Kpende": "Mano Kpende",
    "Mano River": "Mano River",
    "Mano Saija": "Mano Saija",
    "Mano-River": "Mano-River",
    "Mano-Sewallu": "Mano-Sewallu",
    "Manonkoh": "Manonkoh",
    "Manonoko": "Manonoko",
    "Manonokoh": "Manonokoh",
    "Manorhun": "Manorhun",
    "Mansongbo Loko": "Mansongbo Loko",
    "Manthonkoro": "Manthonkoro",
    "Manu": "Manu",
    "Manugbu": "Manugbu",
    "Manunaseh": "Manunaseh",
    "Manungbu": "Manungbu",
    "Manuso Samka": "Manuso Samka",
    "Manusosamka": "Manusosamka",
    "Manussosamka": "Manussosamka",
    "Manye": "Manye",
    "Manyeh": "Manyeh",
    "Manyime": "Manyime",
    "Manyyimmi": "Manyyimmi",
    "Manyymmi": "Manyymmi",
    "Maoda": "Maoda",
    "Maojeh": "Maojeh",
    "Mapaki": "Mapaki",
    "Mapakie": "Mapakie",
    "Mapika": "Mapika",
    "Mapoli": "Mapoli",
    "Mapolie": "Mapolie",
    "Mapollon": "Mapollon",
    "Mapolon": "Mapolon",
    "Mara": "Mara",
    "Marampa": "Marampa",
    "Marefa": "Marefa",
    "Margebla": "Margebla",
    "Marifa": "Marifa",
    "Maron": "Maron",
    "Maronko": "Maronko",
    "Marulu": "Marulu",
    "Maruna Si": "Maruna Si",
    "Maruna Sike": "Maruna Sike",
    "Marunia": "Marunia",
    "Marunia Sakie": "Marunia Sakie",
    "Maruniaseki": "Maruniaseki",
    "Maryu": "Maryu",
    "Masaba": "Masaba",
    "Masabay": "Masabay",
    "Masabong": "Masabong",
    "Masabong Pil": "Masabong Pil",
    "Masabong Pill": "Masabong Pill",
    "Masabong Than": "Masabong Than",
    "Masabong Thoron": "Masabong Thoron",
    "Masabong Thorong": "Masabong Thorong",
    "Masabong Thron": "Masabong Thron",
    "Masabongpil": "Masabongpil",
    "Masabongpill": "Masabongpill",
    "Masabongthoroa": "Masabongthoroa",
    "Masabony Pil": "Masabony Pil",
    "Masagbom Thoron": "Masagbom Thoron",
    "Masagbon Thoron": "Masagbon Thoron",
    "Masah Sety": "Masah Sety",
    "Masah/Setty": "Masah/Setty",
    "Masangbo": "Masangbo",
    "Masapi": "Masapi",
    "Masende Masawma": "Masende Masawma",
    "Maserie": "Maserie",
    "Mashingbi": "Mashingbi",
    "Masingb": "Masingb",
    "Masingbi": "Masingbi",
    "Masingibi": "Masingibi",
    "Masisan": "Masisan",
    "Masobong Thoron": "Masobong Thoron",
    "Masongba": "Masongba",
    "Masongbo": "Masongbo",
    "Masongbo Loko": "Masongbo Loko",
    "Massa Setty": "Massa Setty",
    "Massabanghun": "Massabanghun",
    "Massabong Pill": "Massabong Pill",
    "Massabong Thoron": "Massabong Thoron",
    "Massabong,Pill": "Massabong,Pill",
    "Massapi": "Massapi",
    "Massapi(Makateh)": "Massapi(Makateh)",
    "Massapi(Masokry)": "Massapi(Masokry)",
    "Massaquoi": "Massaquoi",
    "Massaquoi 1": "Massaquoi 1",
    "Massaquoi 11": "Massaquoi 11",
    "Massaquoi 2": "Massaquoi 2",
    "Massaquoi Ii": "Massaquoi Ii",
    "Massaquoi [1]": "Massaquoi [1]",
    "Massaquoi [2]": "Massaquoi [2]",
    "Massaquoi2/Mano River": "Massaquoi2/Mano River",
    "Massasetts": "Massasetts",
    "Massaw": "Massaw",
    "Massawima": "Massawima",
    "Massebay": "Massebay",
    "Masuba": "Masuba",
    "Masyabba": "Masyabba",
    "Matamp": "Matamp",
    "Matanka": "Matanka",
    "Matatie": "Matatie",
    "Matebio": "Matebio",
    "Mateboi": "Mateboi",
    "Mateboi(Section)": "Mateboi(Section)",
    "Matelba": "Matelba",
    "Matene": "Matene",
    "Matetie": "Matetie",
    "Mathanka": "Mathanka",
    "Matheneh": "Matheneh",
    "Mathera": "Mathera",
    "Matherie": "Matherie",
    "Mathirie": "Mathirie",
    "Mathokara": "Mathokara",
    "Mathonka": "Mathonka",
    "Mathonkara": "Mathonkara",
    "Mathorara": "Mathorara",
    "Matie": "Matie",
    "Matilba": "Matilba",
    "Matnine": "Matnine",
    "Maton": "Maton",
    "Matong": "Matong",
    "Matotoka": "Matotoka",
    "Mattru": "Mattru",
    "Mawajeh": "Mawajeh",
    "Mawojeh": "Mawojeh",
    "Mawoma": "Mawoma",
    "Mawonhe": "Mawonhe",
    "Mawullay": "Mawullay",
    "Mayagba": "Mayagba",
    "Mayaha": "Mayaha",
    "Mayakie": "Mayakie",
    "Mayaloh": "Mayaloh",
    "Mayaso": "Mayaso",
    "Mayasso": "Mayasso",
    "Mayatha": "Mayatha",
    "Mayaya": "Mayaya",
    "Mayepoh": "Mayepoh",
    "Mayeppoh": "Mayeppoh",
    "Mayoisor": "Mayoisor",
    "Mayoloh": "Mayoloh",
    "Mayolor": "Mayolor",
    "Mayorloh": "Mayorloh",
    "Mayorsor": "Mayorsor",
    "Mayosor": "Mayosor",
    "Mayosr": "Mayosr",
    "Mayossoh": "Mayossoh",
    "Mbabano": "Mbabano",
    "Mbabao": "Mbabao",
    "Mbabulo": "Mbabulo",
    "Mbawoma": "Mbawoma",
    "Mbawoma Gpenge": "Mbawoma Gpenge",
    "Mbondai": "Mbondai",
    "Mbulie": "Mbulie",
    "Memyyimmi": "Memyyimmi",
    "Menda Gelema": "Menda Gelema",
    "Mende Buima": "Mende Buima",
    "Mende Bujma": "Mende Bujma",
    "Mende Gelema": "Mende Gelema",
    "Mendegdedema": "Mendegdedema",
    "Mendegelema": "Mendegelema",
    "Mendrifeh": "Mendrifeh",
    "Mewa": "Mewa",
    "Mewah": "Mewah",
    "Mile 91": "Mile 91",
    "Mile 91 Gaindema": "Mile 91 Gaindema",
    "Mile 91gaindema": "Mile 91gaindema",
    "Minfinkor": "Minfinkor",
    "Moateh": "Moateh",
    "Mobaii": "Mobaii",
    "Mobail": "Mobail",
    "Mobuiie": "Mobuiie",
    "Mobulie": "Mobulie",
    "Mobullie": "Mobullie",
    "Mofindor": "Mofindor",
    "Mofinkor": "Mofinkor",
    "Mofondo": "Mofondo",
    "Mogbonge": "Mogbonge",
    "Mogeray": "Mogeray",
    "Moideteh": "Moideteh",
    "Moimaligie": "Moimaligie",
    "Moindefeh": "Moindefeh",
    "Moindekoh": "Moindekoh",
    "Moindekor": "Moindekor",
    "Moiwebu": "Moiwebu",
    "Mokaba": "Mokaba",
    "Mokabba": "Mokabba",
    "Mokatawa": "Mokatawa",
    "Mokebbie": "Mokebbie",
    "Mokebbu": "Mokebbu",
    "Mokebie": "Mokebie",
    "Mokenji": "Mokenji",
    "Mokenwo": "Mokenwo",
    "Mokereulo": "Mokereulo",
    "Mokerewo": "Mokerewo",
    "Mokorawo": "Mokorawo",
    "Mokorewo": "Mokorewo",
    "Mokortawa": "Mokortawa",
    "Mokpendeh": "Mokpendeh",
    "Mokuba": "Mokuba",
    "Molatrga": "Molatrga",
    "Momligie": "Momligie",
    "Mommi": "Mommi",
    "Mondogelema": "Mondogelema",
    "Mondor": "Mondor",
    "Mongera": "Mongera",
    "Mongeray": "Mongeray",
    "Mongere": "Mongere",
    "Mongo": "Mongo",
    "Mongor": "Mongor",
    "Monjor": "Monjor",
    "Monkor": "Monkor",
    "Mononiver": "Mononiver",
    "Moore": "Moore",
    "Moria": "Moria",
    "Morku": "Morku",
    "Mosoe": "Mosoe",
    "Motigers": "Motigers",
    "Motindor": "Motindor",
    "Mototoka": "Mototoka",
    "Mowanga": "Mowanga",
    "Mowange": "Mowange",
    "Mowonga": "Mowonga",
    "Mowoto": "Mowoto",
    "Moyandeh": "Moyandeh",
    "Moyeveh": "Moyeveh",
    "Moyoloh": "Moyoloh",
    "Municipal": "Municipal",
    "Musaia": "Musaia",
    "Mye": "Mye",
    "Nagbenteh": "Nagbenteh",
    "Nagbo": "Nagbo",
    "Naiahun": "Naiahun",
    "Nallay": "Nallay",
    "Natatnan": "Natatnan",
    "Ndaa Sei": "Ndaa Sei",
    "Ndaa Sei I": "Ndaa Sei I",
    "Ndabala": "Ndabala",
    "Ndakalele": "Ndakalele",
    "Ndedemoya": "Ndedemoya",
    "Ndieya": "Ndieya",
    "Ndoipeh": "Ndoipeh",
    "Ndopeh": "Ndopeh",
    "Ndopie": "Ndopie",
    "Ndorbeh": "Ndorbeh",
    "Neini": "Neini",
    "Nekpondo": "Nekpondo",
    "Nengen Soro": "Nengen Soro",
    "Nenie": "Nenie",
    "Ngadema": "Ngadema",
    "Nganbu": "Nganbu",
    "Nganyama": "Nganyama",
    "Ngaubu": "Ngaubu",
    "Ngawo": "Ngawo",
    "Ngbengeh": "Ngbengeh",
    "Ngebla": "Ngebla",
    "Ngendema": "Ngendema",
    "Ngepay": "Ngepay",
    "Ngieya": "Ngieya",
    "Ngobapon": "Ngobapon",
    "Ngokpon": "Ngokpon",
    "Ngolala": "Ngolala",
    "Ngolalah": "Ngolalah",
    "Ngolamajeh": "Ngolamajeh",
    "Ngolamajie": "Ngolamajie",
    "Ngolapon": "Ngolapon",
    "Ngoleima": "Ngoleima",
    "Ngombahun": "Ngombahun",
    "Ngova": "Ngova",
    "Ngovo": "Ngovo",
    "Ngovoh": "Ngovoh",
    "Nguabu": "Nguabu",
    "Niagorehum": "Niagorehum",
    "Niagorehun": "Niagorehun",
    "Niahun": "Niahun",
    "Nianyahun": "Nianyahun",
    "Nieima": "Nieima",
    "Nieni": "Nieni",
    "Nimikoro": "Nimikoro",
    "Njabahun": "Njabahun",
    "Njabakahun": "Njabakahun",
    "Njabakalun": "Njabakalun",
    "Njagbahun": "Njagbahun",
    "Njagbakahun": "Njagbakahun",
    "Njagbla": "Njagbla",
    "Njagbla 1": "Njagbla 1",
    "Njagbla 2": "Njagbla 2",
    "Njagbla One": "Njagbla One",
    "Njagbla Two": "Njagbla Two",
    "Njaiama": "Njaiama",
    "Njakor": "Njakor",
    "Njala One": "Njala One",
    "Njama": "Njama",
    "Njaoa": "Njaoa",
    "Njargbahun": "Njargbahun",
    "Njasande Massawima": "Njasande Massawima",
    "Njasende": "Njasende",
    "Njasende Masawima": "Njasende Masawima",
    "Njawa": "Njawa",
    "Njawu": "Njawu",
    "Njaybahun": "Njaybahun",
    "Njebla": "Njebla",
    "Njehun": "Njehun",
    "Njeikor": "Njeikor",
    "Njeima": "Njeima",
    "Njekor": "Njekor",
    "Nonko": "Nonko",
    "Nonkoh": "Nonkoh",
    "Nugurba": "Nugurba",
    "Nuyila": "Nuyila",
    "Nyabu": "Nyabu",
    "Nyala": "Nyala",
    "Nyalay": "Nyalay",
    "Nyalla": "Nyalla",
    "Nyallay": "Nyallay",
    "Nyalley": "Nyalley",
    "Nyallyay": "Nyallyay",
    "Nyandehun": "Nyandehun",
    "Nyango": "Nyango",
    "Nyango-Ngoleihun": "Nyango-Ngoleihun",
    "Nyango-Njeigbla": "Nyango-Njeigbla",
    "Nyangoehun": "Nyangoehun",
    "Nyanyama": "Nyanyama",
    "Nyawa": "Nyawa",
    "Nyawa / Gbeka": "Nyawa / Gbeka",
    "Nyawah": "Nyawah",
    "Nyeima": "Nyeima",
    "Nyellay": "Nyellay",
    "Old Port Loko": "Old Port Loko",
    "Old Town": "Old Town",
    "Oulayor": "Oulayor",
    "Owawor": "Owawor",
    "Paborlah": "Paborlah",
    "Paitfu Bana": "Paitfu Bana",
    "Pakimassabong": "Pakimassabong",
    "Palegbor": "Palegbor",
    "Pangor": "Pangor",
    "Parvu": "Parvu",
    "Pataioo": "Pataioo",
    "Pataloo": "Pataloo",
    "Path Bana": "Path Bana",
    "Patifu": "Patifu",
    "Patifu Bana": "Patifu Bana",
    "Patifu Line": "Patifu Line",
    "Patifu Maboboh": "Patifu Maboboh",
    "Patifu Maborboh": "Patifu Maborboh",
    "Patifu Madina": "Patifu Madina",
    "Patiful Madina": "Patiful Madina",
    "Peje East": "Peje East",
    "Peje Foiya": "Peje Foiya",
    "Peje Foiyia": "Peje Foiyia",
    "Peje West": "Peje West",
    "Pejeh East": "Pejeh East",
    "Pejeh West": "Pejeh West",
    "Pelebloh": "Pelebloh",
    "Pelegbaima": "Pelegbaima",
    "Pelegbambeima": "Pelegbambeima",
    "Pelegbeima": "Pelegbeima",
    "Pelegbloh": "Pelegbloh",
    "Pelegblor": "Pelegblor",
    "Pelegboh": "Pelegboh",
    "Pelegbor": "Pelegbor",
    "Pelegbulor": "Pelegbulor",
    "Pemagbie": "Pemagbie",
    "Penge": "Penge",
    "Pengor": "Pengor",
    "Pesseh": "Pesseh",
    "Pessekeh": "Pessekeh",
    "Pessokeh": "Pessokeh",
    "Petfulime": "Petfulime",
    "Petifu": "Petifu",
    "Petifu Bana": "Petifu Bana",
    "Petifu Line": "Petifu Line",
    "Petifu Madina": "Petifu Madina",
    "Petifuline": "Petifuline",
    "Petitu Line": "Petitu Line",
    "Petituline": "Petituline",
    "Peyaifeh": "Peyaifeh",
    "Peyifeh": "Peyifeh",
    "Pokolie": "Pokolie",
    "Pokorle": "Pokorle",
    "Possokeh": "Possokeh",
    "Potho-Case": "Potho-Case",
    "Ptifu Madina": "Ptifu Madina",
    "Pundhun": "Pundhun",
    "Punthun": "Punthun",
    "R/Bana": "R/Bana",
    "Ragbuay": "Ragbuay",
    "Rasnda": "Rasnda",
    "Remedugu": "Remedugu",
    "Ro Lankonoh": "Ro Lankonoh",
    "Ro-Bia": "Ro-Bia",
    "Ro-Futha": "Ro-Futha",
    "Ro-Sanda": "Ro-Sanda",
    "Robanka": "Robanka",
    "Robart": "Robart",
    "Robat": "Robat",
    "Robauka": "Robauka",
    "Robia": "Robia",
    "Robin": "Robin",
    "Robis": "Robis",
    "Robis Bana": "Robis Bana",
    "Robombeh": "Robombeh",
    "Robonko": "Robonko",
    "Rochain": "Rochain",
    "Rochen": "Rochen",
    "Rofainka": "Rofainka",
    "Rogballan": "Rogballan",
    "Rogbaney": "Rogbaney",
    "Rogbaray": "Rogbaray",
    "Rogbeneny": "Rogbeneny",
    "Rogberay": "Rogberay",
    "Rogberray": "Rogberray",
    "Rogbin": "Rogbin",
    "Rogbonko": "Rogbonko",
    "Rogboreh": "Rogboreh",
    "Rogborreh": "Rogborreh",
    "Rokamerr": "Rokamerr",
    "Rokamken": "Rokamken",
    "Rokankarr": "Rokankarr",
    "Rokankor": "Rokankor",
    "Rokankro": "Rokankro",
    "Rokankrr": "Rokankrr",
    "Rokanta": "Rokanta",
    "Rokel": "Rokel",
    "Rokell": "Rokell",
    "Rokonta": "Rokonta",
    "Rokontor": "Rokontor",
    "Rokupr": "Rokupr",
    "Rolankonoh": "Rolankonoh",
    "Romacca": "Romacca",
    "Romaneh": "Romaneh",
    "Roponka": "Roponka",
    "Roruke": "Roruke",
    "Roruks": "Roruks",
    "Rorules": "Rorules",
    "Rosanda": "Rosanda",
    "Rosarr": "Rosarr",
    "Roses": "Roses",
    "Rosint": "Rosint",
    "Rosint Buya": "Rosint Buya",
    "Rosints": "Rosints",
    "Rosos": "Rosos",
    "Rothatha": "Rothatha",
    "Rounks": "Rounks",
    "Rowollon": "Rowollon",
    "Royeama": "Royeama",
    "Royima": "Royima",
    "Saaba": "Saaba",
    "Saagbengu": "Saagbengu",
    "Saama": "Saama",
    "Saba 1": "Saba 1",
    "Saba 2": "Saba 2",
    "Saba I": "Saba I",
    "Saba Ii": "Saba Ii",
    "Sabba 1": "Sabba 1",
    "Sabba 2": "Sabba 2",
    "Sabba1": "Sabba1",
    "Sabbai": "Sabbai",
    "Sabbal": "Sabbal",
    "Sadugu Wandingo": "Sadugu Wandingo",
    "Safroko": "Safroko",
    "Safroko 2": "Safroko 2",
    "Sagbangu": "Sagbangu",
    "Sahn": "Sahn",
    "Sahn-Gbengu": "Sahn-Gbengu",
    "Sahu": "Sahu",
    "Sahun": "Sahun",
    "Saiama": "Saiama",
    "Saima": "Saima",
    "Saina": "Saina",
    "Sainia": "Sainia",
    "Sakiema": "Sakiema",
    "Sakiema/Sienga": "Sakiema/Sienga",
    "Sakuma": "Sakuma",
    "Sakuna": "Sakuna",
    "Sallma": "Sallma",
    "Salma": "Salma",
    "Sama Gbe": "Sama Gbe",
    "Samagbe": "Samagbe",
    "Samakor": "Samakor",
    "Samamai": "Samamai",
    "Samamaia": "Samamaia",
    "Samami": "Samami",
    "Samamie": "Samamie",
    "Samawa": "Samawa",
    "Samaya": "Samaya",
    "Samba": "Samba",
    "Sambaia": "Sambaia",
    "Sambo": "Sambo",
    "Samia": "Samia",
    "Samiya": "Samiya",
    "Samrba": "Samrba",
    "Samu": "Samu",
    "Samuwa": "Samuwa",
    "Sanamaia": "Sanamaia",
    "Sanda": "Sanda",
    "Sandor": "Sandor",
    "Sandugu": "Sandugu",
    "Sandugu(Yankahala)": "Sandugu(Yankahala)",
    "Sangabu": "Sangabu",
    "Sangbengu": "Sangbengu",
    "Sangor": "Sangor",
    "Sania": "Sania",
    "Sarbah": "Sarbah",
    "Sarjor L": "Sarjor L",
    "Sawa Faima": "Sawa Faima",
    "Sawa Fiama": "Sawa Fiama",
    "Sawabuma": "Sawabuma",
    "Sawafiama": "Sawafiama",
    "Sawakor": "Sawakor",
    "Sawama": "Sawama",
    "Sawana": "Sawana",
    "Seduya": "Seduya",
    "Sei": "Sei",
    "Sei 1": "Sei 1",
    "Sei 2": "Sei 2",
    "Sei I": "Sei I",
    "Sei Ii": "Sei Ii",
    "Sei One": "Sei One",
    "Sei Two": "Sei Two",
    "Sei2": "Sei2",
    "Sei3": "Sei3",
    "Sei4": "Sei4",
    "Seidu": "Seidu",
    "Seikama": "Seikama",
    "Seima": "Seima",
    "Seimaya": "Seimaya",
    "Seing": "Seing",
    "Seitua": "Seitua",
    "Seiwa": "Seiwa",
    "Seiwa Tikonko": "Seiwa Tikonko",
    "Selekoma": "Selekoma",
    "Selemeh": "Selemeh",
    "Selfua": "Selfua",
    "Selima": "Selima",
    "Selimah": "Selimah",
    "Selimeh": "Selimeh",
    "Selokoma": "Selokoma",
    "Semabu": "Semabu",
    "Semamaia": "Semamaia",
    "Sembehun": "Sembehun",
    "Semiya": "Semiya",
    "Sendeh": "Sendeh",
    "Sendeh/Lower Kama": "Sendeh/Lower Kama",
    "Sendugu": "Sendugu",
    "Senehun": "Senehun",
    "Sengudu": "Sengudu",
    "Senjehun": "Senjehun",
    "Sensaila": "Sensaila",
    "Sensehun": "Sensehun",
    "Sentaila": "Sentaila",
    "Sentaila/Bahoin": "Sentaila/Bahoin",
    "Seo Bapewa": "Seo Bapewa",
    "Seobapewa": "Seobapewa",
    "Serabu": "Serabu",
    "Serabu/Sewama": "Serabu/Sewama",
    "Set One": "Set One",
    "Sewa": "Sewa",
    "Sewa Tikonko": "Sewa Tikonko",
    "Sewallu": "Sewallu",
    "Sewalu": "Sewalu",
    "Sewama": "Sewama",
    "Sewana": "Sewana",
    "Sewema": "Sewema",
    "Sewoh": "Sewoh",
    "Sewoma": "Sewoma",
    "Shebora": "Shebora",
    "Siakongafeh": "Siakongafeh",
    "Sie": "Sie",
    "Sienga": "Sienga",
    "Sienga/Dooo": "Sienga/Dooo",
    "Simabaya": "Simabaya",
    "Simbaya": "Simbaya",
    "Simbeya": "Simbeya",
    "Simbonya": "Simbonya",
    "Simiria": "Simiria",
    "Sindeh": "Sindeh",
    "Sinkongoal": "Sinkongoal",
    "Sinkongofeh": "Sinkongofeh",
    "Sinkui0 -2": "Sinkui0 -2",
    "Sinkuina -2": "Sinkuina -2",
    "Sinkunia": "Sinkunia",
    "Sinkunia -1": "Sinkunia -1",
    "Sinkunia -2": "Sinkunia -2",
    "Sinkunia 1": "Sinkunia 1",
    "Sinkunia 2": "Sinkunia 2",
    "Sinkunia-1": "Sinkunia-1",
    "Sinkunia-2": "Sinkunia-2",
    "Sinkunia1": "Sinkunia1",
    "Sinkunia2": "Sinkunia2",
    "Sinni": "Sinni",
    "Socapan": "Socapan",
    "Socapen": "Socapen",
    "Socrapan": "Socrapan",
    "Socrepan": "Socrepan",
    "Socrepan /Momaligie": "Socrepan /Momaligie",
    "Sogonie": "Sogonie",
    "Sograpan": "Sograpan",
    "Sojor I": "Sojor I",
    "Sojor1": "Sojor1",
    "Sokehteh": "Sokehteh",
    "Sokenteh": "Sokenteh",
    "Sokoiteh": "Sokoiteh",
    "Sokoni": "Sokoni",
    "Sokurala": "Sokurala",
    "Sokuralla": "Sokuralla",
    "Solon": "Solon",
    "Somah": "Somah",
    "Somasah": "Somasah",
    "Somiya": "Somiya",
    "Sondor": "Sondor",
    "Sondor 2": "Sondor 2",
    "Sonenteh": "Sonenteh",
    "Songer2": "Songer2",
    "Songo": "Songo",
    "Songoni": "Songoni",
    "Songonie": "Songonie",
    "Sonjor": "Sonjor",
    "Sonjor 1": "Sonjor 1",
    "Sonjor 11": "Sonjor 11",
    "Sonjor 2": "Sonjor 2",
    "Sonjor I": "Sonjor I",
    "Sonjor Ii": "Sonjor Ii",
    "Sonjor L": "Sonjor L",
    "Sonjor2": "Sonjor2",
    "Sonjor2/Dakona": "Sonjor2/Dakona",
    "Sonnah": "Sonnah",
    "Sonneh": "Sonneh",
    "Sopan": "Sopan",
    "Sopan Cleaveland": "Sopan Cleaveland",
    "Sopan-Cleaveland": "Sopan-Cleaveland",
    "Sopan-Cleveland": "Sopan-Cleveland",
    "Sorbeh Grima": "Sorbeh Grima",
    "Soso": "Soso",
    "Sowa": "Sowa",
    "Sulin": "Sulin",
    "Sumbuya": "Sumbuya",
    "Sumunjefeh": "Sumunjefeh",
    "Sumunjifeh": "Sumunjifeh",
    "Sumunjijeh": "Sumunjijeh",
    "Sumyifeh": "Sumyifeh",
    "Supercivland": "Supercivland",
    "Superclvland": "Superclvland",
    "Superclvland:": "Superclvland:",
    "Taama": "Taama",
    "Taama Forest": "Taama Forest",
    "Taama Section": "Taama Section",
    "Taama-One": "Taama-One",
    "Taiama": "Taiama",
    "Taiawa": "Taiawa",
    "Taima Junction": "Taima Junction",
    "Takema": "Takema",
    "Takuno": "Takuno",
    "Takunor": "Takunor",
    "Talama": "Talama",
    "Tama Forest": "Tama Forest",
    "Tamba": "Tamba",
    "Tambiahun": "Tambiahun",
    "Tambiama": "Tambiama",
    "Tamisiama": "Tamisiama",
    "Tamrahun": "Tamrahun",
    "Tangbla": "Tangbla",
    "Tangehun": "Tangehun",
    "Tangla": "Tangla",
    "Tangula": "Tangula",
    "Taninahun": "Taninahun",
    "Taninahun Boka": "Taninahun Boka",
    "Taninahun Kapuima": "Taninahun Kapuima",
    "Taninihun": "Taninihun",
    "Taninihun Mboka": "Taninihun Mboka",
    "Tankor": "Tankor",
    "Tankorio": "Tankorio",
    "Tankoro": "Tankoro",
    "Tanyehun": "Tanyehun",
    "Taokunor": "Taokunor",
    "Tassana": "Tassana",
    "Tassor": "Tassor",
    "Tataima": "Tataima",
    "Tauya": "Tauya",
    "Tawava": "Tawava",
    "Tawkor": "Tawkor",
    "Tawkunor": "Tawkunor",
    "Tawova": "Tawova",
    "Tawovahun": "Tawovahun",
    "Tawuya": "Tawuya",
    "Tayadu": "Tayadu",
    "Technical": "Technical",
    "Tekuno": "Tekuno",
    "Tensekor": "Tensekor",
    "Thama": "Thama",
    "Thankaba": "Thankaba",
    "Tharma Forest": "Tharma Forest",
    "Thawuya": "Thawuya",
    "Thominaya": "Thominaya",
    "Thonkoba": "Thonkoba",
    "Thonkomba": "Thonkomba",
    "Thonkonba": "Thonkonba",
    "Tiasagbia": "Tiasagbia",
    "Tikonko": "Tikonko",
    "Timbo/Kabo": "Timbo/Kabo",
    "Tissagbe": "Tissagbe",
    "Tissana": "Tissana",
    "Tisssana": "Tisssana",
    "Tisssna": "Tisssna",
    "To Dembalenga": "To Dembalenga",
    "To-Ndambalenga": "To-Ndambalenga",
    "Todambalaga": "Todambalaga",
    "Todambalenga": "Todambalenga",
    "Todambalu": "Todambalu",
    "Todambolongar": "Todambolongar",
    "Todambulenge": "Todambulenge",
    "Todaumbalengo": "Todaumbalengo",
    "Todem Balenga": "Todem Balenga",
    "Todembalenga": "Todembalenga",
    "Todenbolega": "Todenbolega",
    "Togorwa": "Togorwa",
    "Toindu": "Toindu",
    "Tokor": "Tokor",
    "Toli": "Toli",
    "Tombay": "Tombay",
    "Tombeh": "Tombeh",
    "Tongawa": "Tongawa",
    "Tongay": "Tongay",
    "Tongea": "Tongea",
    "Tongi Tingi": "Tongi Tingi",
    "Tongieh": "Tongieh",
    "Tongitigi": "Tongitigi",
    "Tongitingi": "Tongitingi",
    "Tongorwa": "Tongorwa",
    "Tongowa": "Tongowa",
    "Tonguwa": "Tonguwa",
    "Tonkoba": "Tonkoba",
    "Tonkoro": "Tonkoro",
    "Tonteh": "Tonteh",
    "Torgowa": "Torgowa",
    "Torli": "Torli",
    "Torma": "Torma",
    "Torma Subu": "Torma Subu",
    "Tossor": "Tossor",
    "Trutle": "Trutle",
    "Tuaker": "Tuaker",
    "Tubla": "Tubla",
    "Tucker /Nyambe": "Tucker /Nyambe",
    "Tucker Nyama": "Tucker Nyama",
    "Tucker Nyamba": "Tucker Nyamba",
    "Tucker Nyambe": "Tucker Nyambe",
    "Tucker-Nyambe": "Tucker-Nyambe",
    "Tucker/ Nyambe": "Tucker/ Nyambe",
    "Tuitansulain": "Tuitansulain",
    "Tuitunsulain": "Tuitunsulain",
    "Tullu": "Tullu",
    "Tumba": "Tumba",
    "Tumuhun": "Tumuhun",
    "Tun-Tun Soloen": "Tun-Tun Soloen",
    "Tun-Tun Sulain": "Tun-Tun Sulain",
    "Tun-Tun Sullay": "Tun-Tun Sullay",
    "Tuntual": "Tuntual",
    "Turma": "Turma",
    "Turtle Island": "Turtle Island",
    "Turtle Islard": "Turtle Islard",
    "Tutle Islard": "Tutle Islard",
    "Tuvu": "Tuvu",
    "U/Georma": "U/Georma",
    "Up/Samie": "Up/Samie",
    "Upper Baima": "Upper Baima",
    "Upper Baimba": "Upper Baimba",
    "Upper Baimber": "Upper Baimber",
    "Upper Bambara": "Upper Bambara",
    "Upper Duiva": "Upper Duiva",
    "Upper Geoma": "Upper Geoma",
    "Upper Georma": "Upper Georma",
    "Upper Greama": "Upper Greama",
    "Upper Kaiyemba": "Upper Kaiyemba",
    "Upper Kaiyenby": "Upper Kaiyenby",
    "Upper Kaiyendgbeh": "Upper Kaiyendgbeh",
    "Upper Kama": "Upper Kama",
    "Upper Kargei": "Upper Kargei",
    "Upper Kargo": "Upper Kargo",
    "Upper Kargoi": "Upper Kargoi",
    "Upper Kawa": "Upper Kawa",
    "Upper Koma": "Upper Koma",
    "Upper Kopmbai": "Upper Kopmbai",
    "Upper Kpombai": "Upper Kpombai",
    "Upper Kpombali": "Upper Kpombali",
    "Upper Kponbali": "Upper Kponbali",
    "Upper Kuiva": "Upper Kuiva",
    "Upper Kuna": "Upper Kuna",
    "Upper Kuvia": "Upper Kuvia",
    "Upper Kuwa": "Upper Kuwa",
    "Upper Masakoh": "Upper Masakoh",
    "Upper Masakor": "Upper Masakor",
    "Upper Maskoh": "Upper Maskoh",
    "Upper Massakong": "Upper Massakong",
    "Upper Mbaima": "Upper Mbaima",
    "Upper Ngeibu": "Upper Ngeibu",
    "Upper Ngiebu": "Upper Ngiebu",
    "Upper Niawa": "Upper Niawa",
    "Upper Nyawa": "Upper Nyawa",
    "Upper Pa Tawo": "Upper Pa Tawo",
    "Upper Patalo": "Upper Patalo",
    "Upper Pataloo": "Upper Pataloo",
    "Upper Pemba": "Upper Pemba",
    "Upper Quiva": "Upper Quiva",
    "Upper Sama": "Upper Sama",
    "Upper Sami": "Upper Sami",
    "Upper Samie": "Upper Samie",
    "Uppermas": "Uppermas",
    "Upperniawa": "Upperniawa",
    "Uppersamie": "Uppersamie",
    "Vaama": "Vaama",
    "Vangalu": "Vangalu",
    "Vangeiu": "Vangeiu",
    "Vanjelu": "Vanjelu",
    "Vargellu": "Vargellu",
    "Vengani": "Vengani",
    "Victoria": "Victoria",
    "W/Mapoth": "W/Mapoth",
    "W0llay": "W0llay",
    "Wahliwahun": "Wahliwahun",
    "Wai": "Wai",
    "Walia": "Walia",
    "Walihun": "Walihun",
    "Waliwahun": "Waliwahun",
    "Warreh Mopoteh": "Warreh Mopoteh",
    "Wayatanda": "Wayatanda",
    "Whindie": "Whindie",
    "Woafeh": "Woafeh",
    "Woateh": "Woateh",
    "Woefeh": "Woefeh",
    "Wollay": "Wollay",
    "Wordu": "Wordu",
    "Worgifor": "Worgifor",
    "Woroma": "Woroma",
    "Worreh Mapoteh": "Worreh Mapoteh",
    "Worreh Mapother": "Worreh Mapother",
    "Wubangay": "Wubangay",
    "Wubange": "Wubange",
    "Wubunge": "Wubunge",
    "Wunde": "Wunde",
    "Yacamboiaie": "Yacamboiaie",
    "Yagala": "Yagala",
    "Yaima": "Yaima",
    "Yainkassa": "Yainkassa",
    "Yainkassa 1": "Yainkassa 1",
    "Yainkassa 11]": "Yainkassa 11]",
    "Yainkassa 1]": "Yainkassa 1]",
    "Yainkassa 2": "Yainkassa 2",
    "Yainkensa": "Yainkensa",
    "Yalenga": "Yalenga",
    "Yallan-gbokie": "Yallan-gbokie",
    "Yallangbokie": "Yallangbokie",
    "Yalmabokie": "Yalmabokie",
    "Yambidu": "Yambidu",
    "Yamkassa L": "Yamkassa L",
    "Yanbidu": "Yanbidu",
    "Yanda": "Yanda",
    "Yando": "Yando",
    "Yandu": "Yandu",
    "Yankabala": "Yankabala",
    "Yankasa 1": "Yankasa 1",
    "Yankasa 2": "Yankasa 2",
    "Yankassa": "Yankassa",
    "Yankassa 2": "Yankassa 2",
    "Yankissa": "Yankissa",
    "Yankobala": "Yankobala",
    "Yankussa": "Yankussa",
    "Yapoma": "Yapoma",
    "Yargbe": "Yargbe",
    "Yarkergu": "Yarkergu",
    "Yarlegu": "Yarlegu",
    "Yarlenga": "Yarlenga",
    "Yartenga": "Yartenga",
    "Yarukassa": "Yarukassa",
    "Yataya": "Yataya",
    "Yawantada": "Yawantada",
    "Yawantanda": "Yawantanda",
    "Yawatanda": "Yawatanda",
    "Yawkassa": "Yawkassa",
    "Yawma": "Yawma",
    "Yebaya": "Yebaya",
    "Yegema": "Yegema",
    "Yeikikabe": "Yeikikabe",
    "Yeinkasa": "Yeinkasa",
    "Yele Manowa": "Yele Manowa",
    "Yele Manowo": "Yele Manowo",
    "Yele Monowo": "Yele Monowo",
    "Yelemanowo": "Yelemanowo",
    "Yelemonowa": "Yelemonowa",
    "Yengema": "Yengema",
    "Yeninkunssa": "Yeninkunssa",
    "Yenkessa": "Yenkessa",
    "Yerlegu": "Yerlegu",
    "Yerlenga": "Yerlenga",
    "Yewkasa": "Yewkasa",
    "Yiehun": "Yiehun",
    "Yogobay": "Yogobay",
    "Yogomaia": "Yogomaia",
    "Yoh": "Yoh",
    "Yokilah": "Yokilah",
    "Yongro": "Yongro",
    "Yoni": "Yoni",
    "Yopoma": "Yopoma",
    "Yorkor": "Yorkor",
    "Yorma": "Yorma",
    "Yoru": "Yoru",
    "Zoker 1": "Zoker 1",
    "Zoker 11/Kai Zomba": "Zoker 11/Kai Zomba",
    "Zoker 2": "Zoker 2",
    "Zoker 3": "Zoker 3",
    "Zoker 4": "Zoker 4",
    "Zoker 5": "Zoker 5",
    "Zoker 6": "Zoker 6",
    "Zoker 7": "Zoker 7",
    "Zoker I": "Zoker I",
    "Zoker [2]": "Zoker [2]",
    "Zoker1": "Zoker1",
    "Zoker2": "Zoker2",
    "Zoker3": "Zoker3",
    "Zoker4": "Zoker4",
    "Zokor 2": "Zokor 2",
    "Zombo 1": "Zombo 1",
    "Zombo 11": "Zombo 11",
    "Zombo 2": "Zombo 2",
    "Zombo Ii": "Zombo Ii",
    "Zombo [1]": "Zombo [1]",
    "Zombo2": "Zombo2",
    "Zomboi": "Zomboi",
    "Zonba": "Zonba",
    "Zowa": "Zowa",
    "Zozo": "Zozo"
}